tox_ignore_env_name_mismatch.py
tox_ignore_env_name_mismatch-0.2.0.post2.dist-info/LICENSE
tox_ignore_env_name_mismatch-0.2.0.post2.dist-info/METADATA
tox_ignore_env_name_mismatch-0.2.0.post2.dist-info/WHEEL
tox_ignore_env_name_mismatch-0.2.0.post2.dist-info/entry_points.txt
tox_ignore_env_name_mismatch-0.2.0.post2.dist-info/top_level.txt
tox_ignore_env_name_mismatch-0.2.0.post2.dist-info/RECORD
