Metadata-Version: 2.1
Name: tox-ignore-env-name-mismatch
Version: 0.2.0.post2
Summary: A tox4 plugin for reusing a virtualenv across multiple test environments.
Author-email: Masen Furer <m_github@0x26.net>
License: MIT License
Project-URL: Homepage, https://github.com/masenf/tox-ignore-env-name-mismatch
Platform: unix
Platform: linux
Platform: osx
Platform: cygwin
Platform: win32
Classifier: Development Status :: 4 - Beta
Classifier: Intended Audience :: Developers
Classifier: License :: OSI Approved :: MIT License
Classifier: Operating System :: POSIX
Classifier: Operating System :: Microsoft :: Windows
Classifier: Operating System :: MacOS :: MacOS X
Classifier: Topic :: Software Development :: Testing
Classifier: Topic :: Software Development :: Libraries
Classifier: Topic :: Utilities
Classifier: Programming Language :: Python
Requires-Python: >=3.7
License-File: LICENSE
